<?xml version="1.0" encoding="UTF-8" ?>
<!DOCTYPE mapper
        PUBLIC "-//mybatis.org//DTD Mapper 3.0//EN"
        "http://mybatis.org/dtd/mybatis-3-mapper.dtd">
<mapper namespace="heyso.HeysoDiaryBackEnd.user.mapper.UserMapper">

    <!-- tb_user -->
    <select id="selectUserById" parameterType="long" resultType="heyso.HeysoDiaryBackEnd.user.model.User">
        SELECT
            user_id,
            email,
            nickname,
            role,
            status,
            token_revoked_after,
            created_at,
            updated_at
        FROM tb_user
        WHERE user_id = #{userId}
    </select>

    <select id="selectUserByEmail" parameterType="string" resultType="heyso.HeysoDiaryBackEnd.user.model.User">
        SELECT
            user_id,
            email,
            nickname,
            role,
            status,
            token_revoked_after,
            created_at,
            updated_at
        FROM tb_user
        WHERE email = #{email}
    </select>

    <insert id="insertUser" parameterType="heyso.HeysoDiaryBackEnd.user.model.User"
            useGeneratedKeys="true" keyProperty="userId">
        INSERT INTO tb_user (
            email, nickname, role, status, created_at, updated_at
        )
        VALUES (
            #{email},
            #{nickname},
            #{role},
            #{status},
            NOW(),
            NOW()
        )
    </insert>

    <!-- tb_user_auth -->
    <select id="selectUserAuthByProviderAndProviderUserId"
            resultType="heyso.HeysoDiaryBackEnd.user.model.UserAuth">
        SELECT
            user_auth_id,
            user_id,
            auth_provider,
            provider_user_id,
            login_id,
            password_hash,
            last_login_at,
            created_at,
            updated_at
        FROM tb_user_auth
        WHERE auth_provider = #{authProvider}
          AND provider_user_id = #{providerUserId}
    </select>

    <select id="selectUserAuthByLoginIdAndProvider"
            resultType="heyso.HeysoDiaryBackEnd.user.model.UserAuth">
        SELECT
            user_auth_id,
            user_id,
            auth_provider,
            provider_user_id,
            login_id,
            password_hash,
            last_login_at,
            created_at,
            updated_at
        FROM tb_user_auth
        WHERE login_id = #{loginId}
          AND auth_provider = #{authProvider}
    </select>

    <select id="selectUserAuthByUserIdAndProvider"
            resultType="heyso.HeysoDiaryBackEnd.user.model.UserAuth">
        SELECT
            user_auth_id,
            user_id,
            auth_provider,
            provider_user_id,
            login_id,
            password_hash,
            last_login_at,
            created_at,
            updated_at
        FROM tb_user_auth
        WHERE user_id = #{userId}
          AND auth_provider = #{authProvider}
    </select>

    <insert id="insertUserAuth" parameterType="heyso.HeysoDiaryBackEnd.user.model.UserAuth"
            useGeneratedKeys="true" keyProperty="userAuthId">
        INSERT INTO tb_user_auth (
            user_id,
            auth_provider,
            provider_user_id,
            login_id,
            password_hash,
            last_login_at,
            created_at,
            updated_at
        )
        VALUES (
            #{userId},
            #{authProvider},
            #{providerUserId},
            #{loginId},
            #{passwordHash},
            NOW(),
            NOW(),
            NOW()
        )
    </insert>

    <update id="updateUserAuthLastLoginAt" parameterType="long">
        UPDATE tb_user_auth
        SET last_login_at = NOW(),
            updated_at    = NOW()
        WHERE user_auth_id = #{userAuthId}
    </update>

    <update id="withdrawUser">
        UPDATE tb_user
        SET email = #{anonymizedEmail},
            nickname = 'withdrawn_user',
            status = 'WITHDRAWN',
            withdrawn_at = NOW(),
            withdraw_reason_cd = #{withdrawReasonCd},
            withdraw_reason_text = #{withdrawReasonText},
            updated_at = NOW()
        WHERE user_id = #{userId}
          AND status = 'ACTIVE'
    </update>

    <delete id="deleteUserAuthByUserId">
        DELETE FROM tb_user_auth
        WHERE user_id = #{userId}
    </delete>

    <update id="updateTokenRevokedAfter">
        UPDATE tb_user
        SET token_revoked_after = #{tokenRevokedAfter},
            updated_at = NOW()
        WHERE user_id = #{userId}
    </update>

</mapper>
